[
  {
    "date": "2032-01-09",
    "name_tr": "KADİR GECESİ"
  },
  {
    "date": "2032-01-13",
    "name_tr": "RAMAZAN BAY. AREFESİ"
  },
  {
    "date": "2032-01-14",
    "name_tr": "RAMAZAN BAYRAMI 1. Gün"
  },
  {
    "date": "2032-01-15",
    "name_tr": "RAMAZAN BAYRAMI 2. Gün"
  },
  {
    "date": "2032-01-16",
    "name_tr": "RAMAZAN BAYRAMI 3. Gün"
  },
  {
    "date": "2032-03-21",
    "name_tr": "KURBAN BAY. AREFESİ"
  },
  {
    "date": "2032-03-22",
    "name_tr": "KURBAN BAYRAMI 1. Gün"
  },
  {
    "date": "2032-03-23",
    "name_tr": "KURBAN BAYRAMI 2. Gün"
  },
  {
    "date": "2032-03-24",
    "name_tr": "KURBAN BAYRAMI 3. Gün"
  },
  {
    "date": "2032-03-25",
    "name_tr": "KURBAN BAYRAMI 4. Gün"
  },
  {
    "date": "2032-04-11",
    "name_tr": "HİCRİ YILBAŞI"
  },
  {
    "date": "2032-04-20",
    "name_tr": "AŞURE GÜNÜ"
  },
  {
    "date": "2032-06-19",
    "name_tr": "MEVLİT KANDİLİ"
  },
  {
    "date": "2032-10-06",
    "name_tr": "ÜÇ AYLARIN BAŞLANGICI"
  },
  {
    "date": "2032-10-07",
    "name_tr": "REGAİB KANDİLİ"
  },
  {
    "date": "2032-11-17",
    "name_tr": "BERAT KANDİLİ"
  },
  {
    "date": "2032-12-04",
    "name_tr": "RAMAZAN BAŞLANGICI"
  },
  {
    "date": "2032-12-29",
    "name_tr": "KADİR GECESİ"
  }
]